snr/__init__.py
snr/__main__.py
snr/cli/__init__.py
snr/cli/atexit_callbacks.py
snr/cli/commands/__init__.py
snr/cli/commands/filesystem.py
snr/cli/commands/misc.py
snr/cli/commands/payload.py
snr/cli/commands/variable.py
snr/cli/gen.py
snr/cli/init.py
snr/cli/interactive_shell.py
snr/cli/lexer.py
snr/cli/main.py
snr/cli/tips.py
snr/cli/variables.py
snr/core/__init__.py
snr/core/core/__init__.py
snr/core/core/arch.py
snr/core/core/common_paths.py
snr/core/core/console.py
snr/core/core/context.py
snr/core/core/logging.py
snr/core/core/options.py
snr/core/core/path_wrapper.py
snr/core/core/variable_manager.py
snr/core/payload/__init__.py
snr/core/payload/context.py
snr/core/payload/data_dir.py
snr/core/payload/entry_point.py
snr/core/payload/nt_registry.py
snr/core/payload/payload.py
snr/core/payload/safety_pin.py
snr/core/payload/storage.py
snr/core/payload/unix_group.py
snr/core/payload/unix_gshadow.py
snr/core/payload/unix_passwd.py
snr/core/payload/unix_shadow.py
snr/core/payload_generation/__init__.py
snr/core/payload_generation/common.py
snr/core/payload_generation/generation.py
snr/core/payload_generation/post/__init__.py
snr/core/payload_generation/post/core_configuration.py
snr/core/payload_generation/post/finishing.py
snr/core/payload_generation/post/grub_installation.py
snr/core/payload_generation/pre/__init__.py
snr/core/payload_generation/pre/ensuring_dependencies.py
snr/core/payload_generation/pre/formatting.py
snr/core/payload_generation/pre/host_check.py
snr/core/payload_generation/pre/partitioning.py
snr/core/payload_generation/pre/rootfs_preparation.py
snr/core/util/__init__.py
snr/core/util/at_formatter.py
snr/core/util/chroot_program_wrapper.py
snr/core/util/chroot_programs.py
snr/core/util/common_utils.py
snr/core/util/download.py
snr/core/util/network_interfaces.py
snr/core/util/payloads/__init__.py
snr/core/util/payloads/autorun.py
snr/core/util/payloads/install_snr_core.py
snr/core/util/payloads/systemd_networkd.py
snr-1.5.2.dist-info/LICENSE
snr-1.5.2.dist-info/METADATA
snr-1.5.2.dist-info/WHEEL
snr-1.5.2.dist-info/entry_points.txt
snr-1.5.2.dist-info/RECORD
