Metadata-Version: 2.1
Name: snr
Version: 1.5.2
Summary: Create bootable payloads easily
Home-page: https://github.com/GlobularOne/snr
License: GPL-3.0
Author: Kamyar
Author-email: 139503563+GlobularOne@users.noreply.github.com
Requires-Python: >=3.11,<4.0
Classifier: License :: OSI Approved :: GNU General Public License v3 (GPLv3)
Classifier: Programming Language :: Python :: 3
Classifier: Programming Language :: Python :: 3.11
Classifier: Programming Language :: Python :: 3.12
Classifier: Programming Language :: Python :: 3.13
Requires-Dist: click (>=8.1.7,<9.0.0)
Requires-Dist: deprecated (>=1.2.14,<2.0.0)
Requires-Dist: prompt-toolkit (>=3.0.47,<4.0.0)
Requires-Dist: psutil (>=6.0.0,<7.0.0)
Requires-Dist: pyfiglet (>=1.0.2,<2.0.0)
Requires-Dist: pygments (>=2.18.0,<3.0.0)
Requires-Dist: requests (>=2.32.3,<3.0.0)
Requires-Dist: rich (>=13.7.1,<14.0.0)
Requires-Dist: setuptools (>=75.6.0,<76.0.0)
Project-URL: Documentation, https://snr.readthedocs.io/en/stable/
Project-URL: Repository, https://github.com/GlobularOne/snr
